{
 "dra": [
  {
   "dra": "http://www.alexa.com/site/help/webmasters",
   "type": "url",
   "file": "/src/tests/uas.js"
  },
  {
   "dra": "http://bsalsa.com/",
   "type": "url",
   "file": "/src/tests/uas.js"
  },
  {
   "dra": "crawler@alexa.com",
   "type": "email",
   "file": "/src/tests/uas.js"
  }
 ],
 "sast": {
  "name": "ua-parser",
  "version": "0.3.5",
  "securityScore": 100,
  "size": "6810735 Bytes",
  "numberOfLines": 11572
 },
 "libraries": [
  {
   "name": "yamlparser",
   "current": "\u003e=0.0.2"
  }
 ]
}